Metadata-Version: 1.2
Name: CryptoContainers
Version: 0.1
Summary: Python module for secure, encrypted file storage
Home-page: https://github.com/L1ghtM4n/CryptoContainer
Author: Lightman
Author-email: L1ghtM3n@protonmail.com
License: UNKNOWN
Platform: UNKNOWN
Classifier: Development Status :: 3 - Alpha
Classifier: Programming Language :: Python :: 3
Classifier: License :: OSI Approved :: MIT License
Classifier: Operating System :: OS Independent
Requires-Python: >=3.8
